pyloggly/__init__.py
pyloggly/handler.py
pyloggly-0.3.0.dist-info/DESCRIPTION.rst
pyloggly-0.3.0.dist-info/METADATA
pyloggly-0.3.0.dist-info/RECORD
pyloggly-0.3.0.dist-info/WHEEL
pyloggly-0.3.0.dist-info/metadata.json
pyloggly-0.3.0.dist-info/top_level.txt
pyloggly-0.3.0.dist-info/zip-safe
