Metadata-Version: 2.0
Name: pyloggly
Version: 0.3.0
Summary: Python logging handler for loggly
Home-page: https://github.com/harvard-dce/pyloggly
Author: Jay Luker
Author-email: lbjay@reallywow.com
License: MIT License
Keywords: loggly logging
Platform: UNKNOWN
Classifier: Development Status :: 3 - Alpha
Classifier: Intended Audience :: Developers
Classifier: Natural Language :: English
Classifier: License :: OSI Approved :: Apache Software License
Classifier: Programming Language :: Python
Classifier: Programming Language :: Python :: 3.6
Classifier: Programming Language :: Python :: 2.7
Requires-Dist: requests-futures
Requires-Dist: python-json-logger
